{
  "dataset_revision": "bbf8b2d84b7de5970b2ba4ea843c791285fdb1df",
  "task_name": "irish-legislative-summaries",
  "mteb_version": "1.38.49",
  "scores": {
    "test": [
      {
        "ndcg_at_1": 0.918,
        "ndcg_at_3": 0.95428,
        "ndcg_at_5": 0.95937,
        "ndcg_at_10": 0.96063,
        "ndcg_at_20": 0.96115,
        "ndcg_at_100": 0.9618,
        "ndcg_at_1000": 0.9618,
        "map_at_1": 0.918,
        "map_at_3": 0.946,
        "map_at_5": 0.9489,
        "map_at_10": 0.9494,
        "map_at_20": 0.94955,
        "map_at_100": 0.94961,
        "map_at_1000": 0.94961,
        "recall_at_1": 0.918,
        "recall_at_3": 0.978,
        "recall_at_5": 0.99,
        "recall_at_10": 0.994,
        "recall_at_20": 0.996,
        "recall_at_100": 1.0,
        "recall_at_1000": 1.0,
        "precision_at_1": 0.918,
        "precision_at_3": 0.326,
        "precision_at_5": 0.198,
        "precision_at_10": 0.0994,
        "precision_at_20": 0.0498,
        "precision_at_100": 0.01,
        "precision_at_1000": 0.001,
        "mrr_at_1": 0.918,
        "mrr_at_3": 0.946,
        "mrr_at_5": 0.9489,
        "mrr_at_10": 0.9494,
        "mrr_at_20": 0.949554,
        "mrr_at_100": 0.949611,
        "mrr_at_1000": 0.949611,
        "nauc_ndcg_at_1_max": 0.683075,
        "nauc_ndcg_at_1_std": -0.542882,
        "nauc_ndcg_at_1_diff1": 0.924677,
        "nauc_ndcg_at_3_max": 0.739729,
        "nauc_ndcg_at_3_std": -0.632723,
        "nauc_ndcg_at_3_diff1": 0.926241,
        "nauc_ndcg_at_5_max": 0.722527,
        "nauc_ndcg_at_5_std": -0.595924,
        "nauc_ndcg_at_5_diff1": 0.925049,
        "nauc_ndcg_at_10_max": 0.72392,
        "nauc_ndcg_at_10_std": -0.587537,
        "nauc_ndcg_at_10_diff1": 0.926837,
        "nauc_ndcg_at_20_max": 0.721955,
        "nauc_ndcg_at_20_std": -0.571954,
        "nauc_ndcg_at_20_diff1": 0.925847,
        "nauc_ndcg_at_100_max": 0.719585,
        "nauc_ndcg_at_100_std": -0.574247,
        "nauc_ndcg_at_100_diff1": 0.925696,
        "nauc_ndcg_at_1000_max": 0.719585,
        "nauc_ndcg_at_1000_std": -0.574247,
        "nauc_ndcg_at_1000_diff1": 0.925696,
        "nauc_map_at_1_max": 0.683075,
        "nauc_map_at_1_std": -0.542882,
        "nauc_map_at_1_diff1": 0.924677,
        "nauc_map_at_3_max": 0.724905,
        "nauc_map_at_3_std": -0.59778,
        "nauc_map_at_3_diff1": 0.925865,
        "nauc_map_at_5_max": 0.716374,
        "nauc_map_at_5_std": -0.577366,
        "nauc_map_at_5_diff1": 0.92524,
        "nauc_map_at_10_max": 0.716743,
        "nauc_map_at_10_std": -0.574597,
        "nauc_map_at_10_diff1": 0.925792,
        "nauc_map_at_20_max": 0.716277,
        "nauc_map_at_20_std": -0.571043,
        "nauc_map_at_20_diff1": 0.925566,
        "nauc_map_at_100_max": 0.716113,
        "nauc_map_at_100_std": -0.571187,
        "nauc_map_at_100_diff1": 0.925555,
        "nauc_map_at_1000_max": 0.716113,
        "nauc_map_at_1000_std": -0.571187,
        "nauc_map_at_1000_diff1": 0.925555,
        "nauc_recall_at_1_max": 0.683075,
        "nauc_recall_at_1_std": -0.542882,
        "nauc_recall_at_1_diff1": 0.924677,
        "nauc_recall_at_3_max": 0.838723,
        "nauc_recall_at_3_std": -0.88231,
        "nauc_recall_at_3_diff1": 0.928699,
        "nauc_recall_at_5_max": 0.789916,
        "nauc_recall_at_5_std": -0.865173,
        "nauc_recall_at_5_diff1": 0.921569,
        "nauc_recall_at_10_max": 0.863834,
        "nauc_recall_at_10_std": -0.870215,
        "nauc_recall_at_10_diff1": 0.956427,
        "nauc_recall_at_20_max": 0.861111,
        "nauc_recall_at_20_std": -0.435341,
        "nauc_recall_at_20_diff1": 0.934641,
        "nauc_recall_at_100_max": NaN,
        "nauc_recall_at_100_std": NaN,
        "nauc_recall_at_100_diff1": NaN,
        "nauc_recall_at_1000_max": NaN,
        "nauc_recall_at_1000_std": NaN,
        "nauc_recall_at_1000_diff1": NaN,
        "nauc_precision_at_1_max": 0.683075,
        "nauc_precision_at_1_std": -0.542882,
        "nauc_precision_at_1_diff1": 0.924677,
        "nauc_precision_at_3_max": 0.838723,
        "nauc_precision_at_3_std": -0.88231,
        "nauc_precision_at_3_diff1": 0.928699,
        "nauc_precision_at_5_max": 0.789916,
        "nauc_precision_at_5_std": -0.865173,
        "nauc_precision_at_5_diff1": 0.921569,
        "nauc_precision_at_10_max": 0.863834,
        "nauc_precision_at_10_std": -0.870215,
        "nauc_precision_at_10_diff1": 0.956427,
        "nauc_precision_at_20_max": 0.861111,
        "nauc_precision_at_20_std": -0.435341,
        "nauc_precision_at_20_diff1": 0.934641,
        "nauc_precision_at_100_max": 1.0,
        "nauc_precision_at_100_std": 1.0,
        "nauc_precision_at_100_diff1": 1.0,
        "nauc_precision_at_1000_max": 1.0,
        "nauc_precision_at_1000_std": 1.0,
        "nauc_precision_at_1000_diff1": 1.0,
        "nauc_mrr_at_1_max": 0.683075,
        "nauc_mrr_at_1_std": -0.542882,
        "nauc_mrr_at_1_diff1": 0.924677,
        "nauc_mrr_at_3_max": 0.724905,
        "nauc_mrr_at_3_std": -0.59778,
        "nauc_mrr_at_3_diff1": 0.925865,
        "nauc_mrr_at_5_max": 0.716374,
        "nauc_mrr_at_5_std": -0.577366,
        "nauc_mrr_at_5_diff1": 0.92524,
        "nauc_mrr_at_10_max": 0.716743,
        "nauc_mrr_at_10_std": -0.574597,
        "nauc_mrr_at_10_diff1": 0.925792,
        "nauc_mrr_at_20_max": 0.716277,
        "nauc_mrr_at_20_std": -0.571043,
        "nauc_mrr_at_20_diff1": 0.925566,
        "nauc_mrr_at_100_max": 0.716113,
        "nauc_mrr_at_100_std": -0.571187,
        "nauc_mrr_at_100_diff1": 0.925555,
        "nauc_mrr_at_1000_max": 0.716113,
        "nauc_mrr_at_1000_std": -0.571187,
        "nauc_mrr_at_1000_diff1": 0.925555,
        "main_score": 0.96063,
        "hf_subset": "default",
        "languages": [
          "eng-Latn"
        ]
      }
    ]
  },
  "evaluation_time": 272.17358469963074,
  "kg_co2_emissions": null
}