{
  "dataset_revision": "bbf8b2d84b7de5970b2ba4ea843c791285fdb1df",
  "task_name": "irish-legislative-summaries",
  "mteb_version": "1.39.7",
  "scores": {
    "test": [
      {
        "ndcg_at_1": 0.702,
        "ndcg_at_3": 0.79278,
        "ndcg_at_5": 0.80732,
        "ndcg_at_10": 0.81978,
        "ndcg_at_20": 0.82691,
        "ndcg_at_100": 0.83322,
        "ndcg_at_1000": 0.83404,
        "map_at_1": 0.702,
        "map_at_3": 0.76967,
        "map_at_5": 0.77757,
        "map_at_10": 0.7828,
        "map_at_20": 0.78478,
        "map_at_100": 0.78578,
        "map_at_1000": 0.78583,
        "recall_at_1": 0.702,
        "recall_at_3": 0.86,
        "recall_at_5": 0.896,
        "recall_at_10": 0.934,
        "recall_at_20": 0.962,
        "recall_at_100": 0.994,
        "recall_at_1000": 1.0,
        "precision_at_1": 0.702,
        "precision_at_3": 0.28667,
        "precision_at_5": 0.1792,
        "precision_at_10": 0.0934,
        "precision_at_20": 0.0481,
        "precision_at_100": 0.00994,
        "precision_at_1000": 0.001,
        "mrr_at_1": 0.702,
        "mrr_at_3": 0.769667,
        "mrr_at_5": 0.777567,
        "mrr_at_10": 0.782797,
        "mrr_at_20": 0.784779,
        "mrr_at_100": 0.785784,
        "mrr_at_1000": 0.785825,
        "nauc_ndcg_at_1_max": 0.588544,
        "nauc_ndcg_at_1_std": -0.286722,
        "nauc_ndcg_at_1_diff1": 0.793241,
        "nauc_ndcg_at_3_max": 0.604232,
        "nauc_ndcg_at_3_std": -0.375924,
        "nauc_ndcg_at_3_diff1": 0.780869,
        "nauc_ndcg_at_5_max": 0.601613,
        "nauc_ndcg_at_5_std": -0.354359,
        "nauc_ndcg_at_5_diff1": 0.76959,
        "nauc_ndcg_at_10_max": 0.591962,
        "nauc_ndcg_at_10_std": -0.376476,
        "nauc_ndcg_at_10_diff1": 0.770852,
        "nauc_ndcg_at_20_max": 0.593283,
        "nauc_ndcg_at_20_std": -0.360192,
        "nauc_ndcg_at_20_diff1": 0.776831,
        "nauc_ndcg_at_100_max": 0.594207,
        "nauc_ndcg_at_100_std": -0.34286,
        "nauc_ndcg_at_100_diff1": 0.776559,
        "nauc_ndcg_at_1000_max": 0.593913,
        "nauc_ndcg_at_1000_std": -0.344654,
        "nauc_ndcg_at_1000_diff1": 0.776585,
        "nauc_map_at_1_max": 0.588544,
        "nauc_map_at_1_std": -0.286722,
        "nauc_map_at_1_diff1": 0.793241,
        "nauc_map_at_3_max": 0.597841,
        "nauc_map_at_3_std": -0.347668,
        "nauc_map_at_3_diff1": 0.782143,
        "nauc_map_at_5_max": 0.596474,
        "nauc_map_at_5_std": -0.335727,
        "nauc_map_at_5_diff1": 0.776624,
        "nauc_map_at_10_max": 0.592812,
        "nauc_map_at_10_std": -0.343266,
        "nauc_map_at_10_diff1": 0.777104,
        "nauc_map_at_20_max": 0.593225,
        "nauc_map_at_20_std": -0.33921,
        "nauc_map_at_20_diff1": 0.77863,
        "nauc_map_at_100_max": 0.593264,
        "nauc_map_at_100_std": -0.336814,
        "nauc_map_at_100_diff1": 0.778496,
        "nauc_map_at_1000_max": 0.593266,
        "nauc_map_at_1000_std": -0.336831,
        "nauc_map_at_1000_diff1": 0.778488,
        "nauc_recall_at_1_max": 0.588544,
        "nauc_recall_at_1_std": -0.286722,
        "nauc_recall_at_1_diff1": 0.793241,
        "nauc_recall_at_3_max": 0.633449,
        "nauc_recall_at_3_std": -0.501337,
        "nauc_recall_at_3_diff1": 0.776805,
        "nauc_recall_at_5_max": 0.630477,
        "nauc_recall_at_5_std": -0.454162,
        "nauc_recall_at_5_diff1": 0.729698,
        "nauc_recall_at_10_max": 0.575941,
        "nauc_recall_at_10_std": -0.673967,
        "nauc_recall_at_10_diff1": 0.718728,
        "nauc_recall_at_20_max": 0.581748,
        "nauc_recall_at_20_std": -0.632439,
        "nauc_recall_at_20_diff1": 0.772495,
        "nauc_recall_at_100_max": 0.664021,
        "nauc_recall_at_100_std": 0.043106,
        "nauc_recall_at_100_diff1": 0.758792,
        "nauc_recall_at_1000_max": NaN,
        "nauc_recall_at_1000_std": NaN,
        "nauc_recall_at_1000_diff1": NaN,
        "nauc_precision_at_1_max": 0.588544,
        "nauc_precision_at_1_std": -0.286722,
        "nauc_precision_at_1_diff1": 0.793241,
        "nauc_precision_at_3_max": 0.633449,
        "nauc_precision_at_3_std": -0.501337,
        "nauc_precision_at_3_diff1": 0.776805,
        "nauc_precision_at_5_max": 0.630477,
        "nauc_precision_at_5_std": -0.454162,
        "nauc_precision_at_5_diff1": 0.729698,
        "nauc_precision_at_10_max": 0.575941,
        "nauc_precision_at_10_std": -0.673967,
        "nauc_precision_at_10_diff1": 0.718728,
        "nauc_precision_at_20_max": 0.581748,
        "nauc_precision_at_20_std": -0.632439,
        "nauc_precision_at_20_diff1": 0.772495,
        "nauc_precision_at_100_max": 0.664021,
        "nauc_precision_at_100_std": 0.043106,
        "nauc_precision_at_100_diff1": 0.758792,
        "nauc_precision_at_1000_max": 1.0,
        "nauc_precision_at_1000_std": 1.0,
        "nauc_precision_at_1000_diff1": 1.0,
        "nauc_mrr_at_1_max": 0.588544,
        "nauc_mrr_at_1_std": -0.286722,
        "nauc_mrr_at_1_diff1": 0.793241,
        "nauc_mrr_at_3_max": 0.597841,
        "nauc_mrr_at_3_std": -0.347668,
        "nauc_mrr_at_3_diff1": 0.782143,
        "nauc_mrr_at_5_max": 0.596474,
        "nauc_mrr_at_5_std": -0.335727,
        "nauc_mrr_at_5_diff1": 0.776624,
        "nauc_mrr_at_10_max": 0.592812,
        "nauc_mrr_at_10_std": -0.343266,
        "nauc_mrr_at_10_diff1": 0.777104,
        "nauc_mrr_at_20_max": 0.593225,
        "nauc_mrr_at_20_std": -0.33921,
        "nauc_mrr_at_20_diff1": 0.77863,
        "nauc_mrr_at_100_max": 0.593264,
        "nauc_mrr_at_100_std": -0.336814,
        "nauc_mrr_at_100_diff1": 0.778496,
        "nauc_mrr_at_1000_max": 0.593266,
        "nauc_mrr_at_1000_std": -0.336831,
        "nauc_mrr_at_1000_diff1": 0.778488,
        "main_score": 0.81978,
        "hf_subset": "default",
        "languages": [
          "eng-Latn"
        ]
      }
    ]
  },
  "evaluation_time": 14.569701671600342,
  "kg_co2_emissions": null
}